machinelogic/__init__.py
machinelogic/decorators/__init__.py
machinelogic/decorators/deprecated.py
machinelogic/decorators/future_api.py
machinelogic/decorators/tests/__init__.py
machinelogic/decorators/tests/test_deprecated.py
machinelogic/decorators/tests/test_future_api.py
machinelogic/decorators/tests/test_undocumented.py
machinelogic/decorators/undocumented.py
machinelogic/ivention/__init__.py
machinelogic/ivention/event_listener.py
machinelogic/ivention/exception.py
machinelogic/ivention/handle.py
machinelogic/ivention/iac_motor.py
machinelogic/ivention/iactuator.py
machinelogic/ivention/iactuator_group.py
machinelogic/ivention/icalibration_frame.py
machinelogic/ivention/icamera.py
machinelogic/ivention/icartesian_target.py
machinelogic/ivention/idigital_input.py
machinelogic/ivention/idigital_io_shared.py
machinelogic/ivention/idigital_output.py
machinelogic/ivention/igeneric_joint_constraint.py
machinelogic/ivention/ijoint_target.py
machinelogic/ivention/imachine.py
machinelogic/ivention/imachine_motion.py
machinelogic/ivention/ipath_follower.py
machinelogic/ivention/ipneumatic.py
machinelogic/ivention/ireference_frame.py
machinelogic/ivention/irobot.py
machinelogic/ivention/iscene.py
machinelogic/ivention/machine_configuration.py
machinelogic/ivention/mqtt_client.py
machinelogic/ivention/tests/__init__.py
machinelogic/ivention/tests/test_batch_move.py
machinelogic/ivention/tests/test_event_listener.py
machinelogic/ivention/tests/test_icartesian_target.py
machinelogic/ivention/tests/test_idigital_input.py
machinelogic/ivention/tests/test_idigital_output.py
machinelogic/ivention/tests/test_igeneric_joint_constraint.py
machinelogic/ivention/tests/test_ijoint_target.py
machinelogic/ivention/tests/test_imachine.py
machinelogic/ivention/tests/test_ipath_follower.py
machinelogic/ivention/tests/test_ireference_frame.py
machinelogic/ivention/tests/test_irobot.py
machinelogic/ivention/tests/test_mqtt_client.py
machinelogic/ivention/types/__init__.py
machine_logic_sdk-2.2.0.dist-info/METADATA
machine_logic_sdk-2.2.0.dist-info/WHEEL
machine_logic_sdk-2.2.0.dist-info/RECORD
