Metadata-Version: 2.4
Name: machine-logic-sdk
Version: 2.2.0
Summary: SDK for controlling Vention hardware
License: Proprietary
Keywords: Vention,MachineLogic,SDK,Robot,Automation
Author: VentionCo
Requires-Python: >=3.10,<3.11
Classifier: License :: Other/Proprietary License
Classifier: Operating System :: POSIX :: Linux
Classifier: Programming Language :: Python :: 3
Classifier: Programming Language :: Python :: 3.10
Classifier: Programming Language :: Python :: 3.9
Requires-Dist: docstring-parser (>=0.16,<0.17)
Requires-Dist: numpy (>=1.21,<2.0)
Requires-Dist: paho-mqtt (>=1.5,<2.0)
Requires-Dist: python-statemachine (>=2.5,<3.0)
Requires-Dist: requests (>=2.28,<3.0)
Requires-Dist: roslibpy (>=1.4,<2.0)
Requires-Dist: scipy (>=1.8,<2.0)
Requires-Dist: toml (>=0.10,<0.11)
Requires-Dist: typing_extensions (>=4.8,<5.0)
Requires-Dist: uv (>=0.6,<0.7)
Project-URL: Documentation, https://vention.io/resources/guides/machinelogic-python-programming-514
